[{"nik":1,"nama":"Utama Wijaya S.I.Kom","alamat":"Ki. Kartini No. 704, Bandar Lampung 44381, DKI","tanggal":"1981-07-09 21:00:18","phone":"(+62) 246 6889 6120"},
{"nik":2,"nama":"Padmi Permata S.E.I","alamat":"Jr. Labu No. 812, Serang 69124, Riau","tanggal":"2013-12-02 07:07:16","phone":"(+62) 975 0640 7715"},
{"nik":3,"nama":"Victoria Paris Yulianti","alamat":"Jln. Rajawali Barat No. 416, Padangsidempuan 14272, Bali","tanggal":"1991-08-21 01:44:32","phone":"0956 8461 668"},
{"nik":4,"nama":"Putu Mahmud Pradana","alamat":"Gg. Laksamana No. 116, Pematangsiantar 80420, Sulbar","tanggal":"1976-08-26 14:59:55","phone":"020 2200 296"},
{"nik":5,"nama":"Yosef Sihombing S.Kom","alamat":"Kpg. Wora Wari No. 691, Palembang 23978, Babel","tanggal":"2022-10-09 23:55:19","phone":"0454 2032 589"},
{"nik":6,"nama":"Gamani Damanik M.M.","alamat":"Ki. Camar No. 647, Madiun 85431, NTB","tanggal":"1993-03-19 01:43:30","phone":"0886 8153 5613"},
{"nik":7,"nama":"Cakrajiya Nainggolan","alamat":"Psr. Abdullah No. 569, Magelang 77460, Jabar","tanggal":"2011-10-11 05:44:13","phone":"(+62) 913 8273 2174"},
{"nik":8,"nama":"Ade Dongoran","alamat":"Psr. Baabur Royan No. 512, Gorontalo 69014, Aceh","tanggal":"2015-11-05 23:01:45","phone":"(+62) 720 0062 1941"},
{"nik":9,"nama":"Empluk Sitompul S.Gz","alamat":"Kpg. Honggowongso No. 986, Magelang 10262, Bengkulu","tanggal":"2019-03-16 13:22:10","phone":"0338 6369 977"},
{"nik":10,"nama":"Zulaikha Farida","alamat":"Dk. Aceh No. 200, Gunungsitoli 91733, Kalsel","tanggal":"1971-01-27 19:25:13","phone":"0374 3979 955"},
{"nik":11,"nama":"Legawa Rajata","alamat":"Dk. K.H. Wahid Hasyim (Kopo) No. 250, Semarang 98365, Malut","tanggal":"1972-06-26 08:09:05","phone":"(+62) 649 1613 5284"},
{"nik":12,"nama":"Balidin Yusuf Saragih","alamat":"Gg. W.R. Supratman No. 534, Bogor 49631, NTT","tanggal":"1980-10-08 00:08:56","phone":"0852 9501 0614"},
{"nik":13,"nama":"Padmi Endah Namaga S.T.","alamat":"Ds. Bak Air No. 399, Semarang 50242, Jambi","tanggal":"1996-07-20 16:06:27","phone":"0573 4455 849"},
{"nik":14,"nama":"Dina Wijayanti","alamat":"Dk. Raden No. 416, Palu 67659, NTT","tanggal":"1974-09-14 10:44:10","phone":"0992 0650 176"},
{"nik":15,"nama":"Narji Edison Januar S.Psi","alamat":"Jln. Sutan Syahrir No. 30, Tegal 22310, DIY","tanggal":"2006-09-12 00:28:31","phone":"0854 3546 161"},
{"nik":16,"nama":"Nugraha Simanjuntak","alamat":"Ki. Otista No. 123, Bima 23611, Kalbar","tanggal":"2020-03-05 17:40:35","phone":"0296 0465 5995"},
{"nik":17,"nama":"Dipa Asirwada Januar S.Farm","alamat":"Gg. Tentara Pelajar No. 498, Batu 12926, Sultra","tanggal":"1976-03-13 04:01:18","phone":"0299 3122 024"},
{"nik":18,"nama":"Janet Wirda Lailasari","alamat":"Ki. Barat No. 312, Subulussalam 84566, Kalbar","tanggal":"1996-11-04 22:30:41","phone":"029 6522 000"},
{"nik":19,"nama":"Labuh Kacung Mahendra M.Ak","alamat":"Jr. Basoka Raya No. 770, Banda Aceh 94273, Sumbar","tanggal":"1996-07-20 08:01:45","phone":"(+62) 557 6421 5714"},
{"nik":20,"nama":"Liman Catur Hakim","alamat":"Dk. Agus Salim No. 665, Kotamobagu 63891, Sultra","tanggal":"1984-11-24 13:56:06","phone":"(+62) 907 2970 9107"},
{"nik":21,"nama":"Ikhsan Prabowo","alamat":"Jln. Pasteur No. 70, Bima 81701, NTB","tanggal":"1970-01-12 11:01:31","phone":"0628 3557 786"},
{"nik":22,"nama":"Dimas Napitupulu","alamat":"Ki. Baranang No. 87, Pontianak 76301, Riau","tanggal":"1992-10-14 16:11:51","phone":"(+62) 854 3081 4575"},
{"nik":23,"nama":"Salsabila Pudjiastuti S.Psi","alamat":"Ds. Sutoyo No. 633, Bitung 20397, NTT","tanggal":"2014-11-08 19:12:17","phone":"0929 9286 7403"},
{"nik":24,"nama":"Karen Purnawati","alamat":"Jr. Jend. A. Yani No. 307, Sabang 48925, Sumut","tanggal":"1970-09-11 10:10:26","phone":"0853 0981 0287"},
{"nik":25,"nama":"Nyana Wahyudin S.Gz","alamat":"Jln. Bakaru No. 9, Tangerang 40862, Jateng","tanggal":"1999-08-24 11:00:09","phone":"0842 611 911"},
{"nik":26,"nama":"Putri Rahmawati","alamat":"Jr. Abdul No. 240, Sorong 57200, Jambi","tanggal":"2009-11-26 15:09:38","phone":"(+62) 727 2724 778"},
{"nik":27,"nama":"Zulfa Utami","alamat":"Ds. Bak Mandi No. 561, Salatiga 28840, Babel","tanggal":"1981-02-24 01:21:24","phone":"(+62) 880 9549 054"},
{"nik":28,"nama":"Gina Wastuti M.TI.","alamat":"Kpg. Yos No. 982, Madiun 50271, Jateng","tanggal":"1990-05-31 23:09:23","phone":"(+62) 23 8854 6589"},
{"nik":29,"nama":"Among Adriansyah","alamat":"Kpg. Bara No. 489, Palangka Raya 90547, Babel","tanggal":"2016-06-06 23:37:20","phone":"(+62) 603 6851 204"},
{"nik":30,"nama":"Bambang Gaduh Pranowo M.Ak","alamat":"Ki. Bappenas No. 629, Sawahlunto 39800, Sumut","tanggal":"1988-10-25 10:22:50","phone":"(+62) 554 7921 439"},
{"nik":31,"nama":"Bajragin Prasetyo","alamat":"Jln. Wahid Hasyim No. 279, Mataram 45254, Kepri","tanggal":"2016-06-09 07:00:32","phone":"(+62) 608 0523 470"},
{"nik":32,"nama":"Bagya Saefullah S.E.I","alamat":"Dk. Sukabumi No. 386, Pasuruan 94447, Sulteng","tanggal":"1978-07-03 19:23:53","phone":"(+62) 716 8223 1908"},
{"nik":33,"nama":"Ani Betania Rahimah","alamat":"Ki. Sutarjo No. 250, Tual 60785, DKI","tanggal":"2016-12-08 08:44:36","phone":"(+62) 771 4131 359"},
{"nik":34,"nama":"Titi Mulyani S.I.Kom","alamat":"Ds. Honggowongso No. 412, Tasikmalaya 92252, Malut","tanggal":"1985-06-23 07:55:56","phone":"(+62) 947 1209 1480"},
{"nik":35,"nama":"Timbul Saefullah","alamat":"Jr. Bak Air No. 839, Bengkulu 18766, Jatim","tanggal":"1998-05-05 10:42:51","phone":"0599 4077 397"},
{"nik":36,"nama":"Natalia Mardhiyah","alamat":"Psr. Surapati No. 747, Administrasi Jakarta Timur 51001, Gorontalo","tanggal":"1981-10-31 06:16:55","phone":"(+62) 993 3852 283"},
{"nik":37,"nama":"Jabal Pranata Tampubolon","alamat":"Dk. Baing No. 729, Palangka Raya 17151, Papua","tanggal":"1989-05-08 11:18:00","phone":"(+62) 444 5782 8975"},
{"nik":38,"nama":"Warta Pradipta","alamat":"Psr. Bazuka Raya No. 783, Dumai 13319, Sumsel","tanggal":"1985-09-10 01:17:25","phone":"0988 6587 135"},
{"nik":39,"nama":"Jefri Prasetya","alamat":"Ki. Yap Tjwan Bing No. 37, Surabaya 70399, Banten","tanggal":"2012-08-24 01:10:37","phone":"(+62) 968 7636 9958"},
{"nik":40,"nama":"Septi Nasyidah","alamat":"Ds. Bakin No. 310, Padangpanjang 19894, Jabar","tanggal":"2013-06-25 19:36:55","phone":"0658 0312 3962"},
{"nik":41,"nama":"Kezia Diana Nuraini","alamat":"Jln. Jambu No. 990, Depok 29516, Kalsel","tanggal":"1979-08-10 13:25:45","phone":"(+62) 972 6198 5642"},
{"nik":42,"nama":"Yani Suartini","alamat":"Psr. Batako No. 171, Padang 61343, Malut","tanggal":"1977-03-29 06:49:57","phone":"(+62) 726 7779 9703"},
{"nik":43,"nama":"Elisa Intan Kuswandari M.Kom.","alamat":"Psr. Gotong Royong No. 666, Surakarta 21990, Sumut","tanggal":"1987-09-16 20:51:54","phone":"0952 8008 238"},
{"nik":44,"nama":"Martana Martani Sitorus M.Pd","alamat":"Jr. Raden No. 549, Surabaya 61998, Kaltara","tanggal":"1996-12-07 00:00:02","phone":"(+62) 968 7670 022"},
{"nik":45,"nama":"Paulin Agustina","alamat":"Ds. Jaksa No. 515, Bukittinggi 60355, NTT","tanggal":"1970-03-24 23:48:06","phone":"(+62) 643 6351 2525"},
{"nik":46,"nama":"Lasmanto Harto Megantara S.T.","alamat":"Ds. Ters. Pasir Koja No. 595, Banjarmasin 39488, DIY","tanggal":"1993-04-16 05:33:57","phone":"(+62) 852 273 508"},
{"nik":47,"nama":"Prabowo Dongoran S.H.","alamat":"Ds. Mulyadi No. 654, Tidore Kepulauan 82528, Aceh","tanggal":"1970-02-03 07:36:40","phone":"0981 4843 7277"},
{"nik":48,"nama":"Luluh Napitupulu","alamat":"Jr. Bak Air No. 595, Tanjungbalai 57133, Jateng","tanggal":"1984-09-07 11:15:51","phone":"(+62) 392 2863 0484"},
{"nik":49,"nama":"Nabila Widiastuti","alamat":"Ki. Gremet No. 868, Palembang 87467, Bengkulu","tanggal":"2019-10-05 22:53:46","phone":"0239 5775 725"},
{"nik":50,"nama":"Zulfa Astuti","alamat":"Dk. Bah Jaya No. 806, Bitung 58716, Kepri","tanggal":"1990-05-26 14:48:42","phone":"(+62) 984 3712 000"}]